sopnmf/__init__.py
sopnmf/base.py
sopnmf/cli.py
sopnmf/main.py
sopnmf/opnmf_core.py
sopnmf/opnmf_post.py
sopnmf/utils.py
sopnmf/workflow.py
sopnmf-0.0.4.dist-info/LICENSE
sopnmf-0.0.4.dist-info/METADATA
sopnmf-0.0.4.dist-info/WHEEL
sopnmf-0.0.4.dist-info/entry_points.txt
sopnmf-0.0.4.dist-info/top_level.txt
sopnmf-0.0.4.dist-info/RECORD
