Metadata-Version: 2.1
Name: sopnmf
Version: 0.0.4
Summary: Stochastic Orthogonal Projective Non-negative Matrix Factorization
Home-page: https://github.com/anbai106/SOPNMF
Author: junhao.wen
Author-email: junhao.wen89@email.com
License: UNKNOWN
Platform: UNKNOWN
Classifier: Programming Language :: Python :: 3
Classifier: License :: OSI Approved :: MIT License
Classifier: Operating System :: OS Independent
License-File: LICENSE
